LICENSE.txt
README.rst
setup.cfg
setup.py
src/codeviking.math.egg-info/PKG-INFO
src/codeviking.math.egg-info/SOURCES.txt
src/codeviking.math.egg-info/dependency_links.txt
src/codeviking.math.egg-info/not-zip-safe
src/codeviking.math.egg-info/requires.txt
src/codeviking.math.egg-info/top_level.txt
src/codeviking/math/__init__.py
src/codeviking/math/_version.py
src/codeviking/math/angle.py
src/codeviking/math/comparisons.py
src/codeviking/math/ease.py
src/codeviking/math/functions.py
src/codeviking/math/geom2d.py
src/codeviking/math/interval.py
src/codeviking/math/linalg.py
src/codeviking/math/primitives.py
test/test_angle.py
test/test_comparisons.py
test/test_functions.py
test/test_geom.py
test/test_interval.py
test/test_segment.py