Metadata-Version: 2.1
Name: codeviking.math
Version: 0.20.2
Summary: Function and method call math
Home-page: https://bitbucket.org/codeviking/python-codeviking.math/
Author: Dan Bullok
Author-email: opensource@codeviking.com
License: ISC
Platform: any
Classifier: Development Status :: 4 - Beta
Classifier: Intended Audience :: Developers
Classifier: License :: OSI Approved
Classifier: License :: OSI Approved :: ISC License (ISCL)
Classifier: Natural Language :: English
Classifier: Operating System :: OS Independent
Classifier: Programming Language :: Python
Classifier: Programming Language :: Python :: 3
Classifier: Programming Language :: Python :: 3 :: Only
Classifier: Topic :: Software Development :: Libraries :: Python Modules
Classifier: Topic :: Scientific/Engineering :: Mathematics
License-File: LICENSE.txt
